{"status":"done","publicPath":"http://127.0.0.1:8080/","chunks":{"app":[{"name":"bundle.css","publicPath":"http://127.0.0.1:8080/bundle.css","path":"C:\\Users\\Kasia\\inżynierka\\11.09.2021\\SYLKOS\\frontend\\dist\\bundle.css"},{"name":"bundle.js","publicPath":"http://127.0.0.1:8080/bundle.js","path":"C:\\Users\\Kasia\\inżynierka\\11.09.2021\\SYLKOS\\frontend\\dist\\bundle.js"},{"name":"app.8d0c39c7f96e5bf12245.hot-update.js","publicPath":"http://127.0.0.1:8080/app.8d0c39c7f96e5bf12245.hot-update.js","path":"C:\\Users\\Kasia\\inżynierka\\11.09.2021\\SYLKOS\\frontend\\dist\\app.8d0c39c7f96e5bf12245.hot-update.js"}]},"error":"ModuleError","message":"Module Error (from ./node_modules/eslint-loader/index.js):\n\nC:\\Users\\Kasia\\inżynierka\\11.09.2021\\SYLKOS\\frontend\\src\\common\\api.service.js\n  25:42  error  Unreachable code  no-unreachable\n\n✖ 1 problem (1 error, 0 warnings)\n"}